{ 
   "Departments": [
      {
         "ID": "1",
         "ParentID": "-1",
         "ImageIndex": "0",
         "Department": "Corporate Headquarters",
         "Budget": "1000000",
         "Location": "Monterey",
         "Phone": "(408) 555-1234",
         "LastOrder": "2008-02-15T00:00:00.0000000",
         "Check": "false"
      },
      {
         "ID": "2",
         "ParentID": "1",
         "ImageIndex": "1",
         "Department": "Sales and Marketing",
         "Budget": "22000",
         "Location": "San Francisco",
         "Phone": "(415) 555-1234",
         "LastOrder": "2006-03-05T00:00:00.0000000",
         "Check": "true"
      },
      {
         "ID": "3",
         "ParentID": "2",
         "ImageIndex": "4",
         "Department": "Field Office: Canada",
         "Budget": "500000",
         "Location": "Toronto",
         "Phone": "(416) 677-1000",
         "LastOrder": "2009-05-01T00:00:00.0000000",
         "Check": "false"
      },
      {
         "ID": "4",
         "ParentID": "2",
         "ImageIndex": "4",
         "Department": "Field Office: East Coast",
         "Budget": "500000",
         "Location": "Boston",
         "Phone": "(617) 555-4234",
         "LastOrder": "2011-05-05T00:00:00.0000000",
         "Check": "true"
      },
      {
         "ID": "5",
         "ParentID": "2",
         "ImageIndex": "4",
         "Department": "Pacific Rim Headquarters",
         "Budget": "600000",
         "Location": "Kuaui",
         "Phone": "(808) 555-1234",
         "LastOrder": "2007-05-25T00:00:00.0000000",
         "Check": "false"
      },
      {
         "ID": "6",
         "ParentID": "5",
         "ImageIndex": "6",
         "Department": "Field Office: Singapore",
         "Budget": "300000",
         "Location": "Singapore",
         "Phone": "(606) 555-5486",
         "LastOrder": "2009-07-15T00:00:00.0000000",
         "Check": "false"
      },
      {
         "ID": "7",
         "ParentID": "5",
         "ImageIndex": "6",
         "Department": "Field Office: Japan",
         "Budget": "500000",
         "Location": "Tokyo",
         "Phone": "(707) 555-1526",
         "LastOrder": "2008-08-05T00:00:00.0000000",
         "Check": "false"
      },
      {
         "ID": "8",
         "ParentID": "2",
         "ImageIndex": "4",
         "Department": "Marketing",
         "Budget": "1500000",
         "Location": "San Francisco",
         "Phone": "(415) 555-1234",
         "LastOrder": "2008-09-17T00:00:00.0000000",
         "Check": "true"
      },
      {
         "ID": "9",
         "ParentID": "1",
         "ImageIndex": "2",
         "Department": "Finance",
         "Budget": "40000",
         "Location": "Monterey",
         "Phone": "(408) 555-1234",
         "LastOrder": "2011-05-05T00:00:00.0000000",
         "Check": "true"
      },
      {
         "ID": "10",
         "ParentID": "1",
         "ImageIndex": "3",
         "Department": "Engineering",
         "Budget": "1100000",
         "Location": "Monterey",
         "Phone": "(408) 555-1234",
         "LastOrder": "2008-08-12T00:00:00.0000000",
         "Check": "true"
      },
      {
         "ID": "11",
         "ParentID": "10",
         "ImageIndex": "5",
         "Department": "Consumer Electronics Div.",
         "Budget": "1150000",
         "Location": "Burlington, VT",
         "Phone": "(802) 555-1234",
         "LastOrder": "2010-05-10T00:00:00.0000000",
         "Check": "true"
      },
      {
         "ID": "12",
         "ParentID": "11",
         "ImageIndex": "6",
         "Department": "Software Development",
         "Budget": "40000",
         "Location": "Monterey",
         "Phone": "(408) 555-1234",
         "LastOrder": "2008-08-05T00:00:00.0000000",
         "Check": "true"
      },
      {
         "ID": "13",
         "ParentID": "10",
         "ImageIndex": "5",
         "Department": "Software Products Div.",
         "Budget": "1200000",
         "Location": "Monterey",
         "Phone": "(408) 555-1234",
         "LastOrder": "2008-11-11T00:00:00.0000000",
         "Check": "true"
      },
      {
         "ID": "14",
         "ParentID": "13",
         "ImageIndex": "6",
         "Department": "Quality Assurance",
         "Budget": "48000",
         "Location": "Monterey",
         "Phone": "(408) 555-1234",
         "LastOrder": "2009-05-08T00:00:00.0000000",
         "Check": "false"
      },
      {
         "ID": "15",
         "ParentID": "13",
         "ImageIndex": "6",
         "Department": "Customer Support",
         "Budget": "38000",
         "Location": "Monterey",
         "Phone": "(408) 555-1234",
         "LastOrder": "2008-12-05T00:00:00.0000000",
         "Check": "false"
      },
      {
         "ID": "16",
         "ParentID": "13",
         "ImageIndex": "6",
         "Department": "Research and Development",
         "Budget": "460000",
         "Location": "Burlington, VT",
         "Phone": "(802) 555-1234",
         "LastOrder": "2008-10-15T00:00:00.0000000",
         "Check": "true"
      },
      {
         "ID": "17",
         "ParentID": "13",
         "ImageIndex": "6",
         "Department": "Customer Services",
         "Budget": "850000",
         "Location": "Burlington, VT",
         "Phone": "(802) 555-1234",
         "LastOrder": "2011-05-05T00:00:00.0000000",
         "Check": "true"
      }
   ]
}